rtl/dmem.v
module dmem (
    input clk, mem_write, mem_read,
    input [31:0] addr, wd,
    output [31:0] rd
);
    reg [31:0] mem [0:63];
    assign rd = mem[addr[7:2]];
    always @(posedge clk)
        if (mem_write) mem[addr[7:2]] <= wd;
endmodule

rtl/alu.v
module alu (
    input  [31:0] a, b,
    input  [3:0]  alu_ctrl,   // 0=ADD 1=SUB 2=AND 3=OR
    output reg [31:0] result,
    output zero               // used by BEQ
);
    always @(*) begin
        case (alu_ctrl)
            4'b0000: result = a + b;
            4'b0001: result = a - b;
            4'b0010: result = a & b;
            4'b0011: result = a | b;
            default: result = 32'b0;
        endcase
    end
    assign zero = (result == 32'b0);
endmodule

rtl/regfile.v
module regfile (
    input clk,
    input [4:0] rs1, rs2, rd,
    input [31:0] wd,
    input we,
    output [31:0] rd1, rd2
);
    reg [31:0] regs [0:31];
    assign rd1 = (rs1 == 0) ? 32'b0 : regs[rs1];
    assign rd2 = (rs2 == 0) ? 32'b0 : regs[rs2];

    always @(posedge clk)
        if (we && rd != 0)
            regs[rd] <= wd;
endmodule

rtl/control.v
module control (
    input  [6:0] opcode,
    output reg reg_write, alu_src, mem_write, mem_read, mem_to_reg, branch,
    output reg [1:0] alu_op
);
    always @(*) begin
        {reg_write, alu_src, mem_write, mem_read, mem_to_reg, branch, alu_op} = 0;
        case (opcode)
            7'b0110011: begin reg_write=1; alu_op=2'b10; end                     // R-type
            7'b0010011: begin reg_write=1; alu_src=1; alu_op=2'b00; end          // ADDI
            7'b0000011: begin reg_write=1; alu_src=1; mem_read=1; mem_to_reg=1; end // LW
            7'b0100011: begin alu_src=1; mem_write=1; end                        // SW
            7'b1100011: begin branch=1; alu_op=2'b01; end                       // BEQ
        endcase
    end
endmodule

rtl/imem.v
module imem (
    input [31:0] addr,
    output [31:0] instr
);
    reg [31:0] mem [0:63];
    initial $readmemh("sw/program.hex", mem);
    assign instr = mem[addr[7:2]];   // word-aligned
endmodule

rtl/cpu.v
module cpu (input clk, reset);
    reg [31:0] pc;
    wire [31:0] instr, imm, rd1, rd2, alu_b, alu_result, mem_rd, wb_data;
    wire reg_write, alu_src, mem_write, mem_read, mem_to_reg, branch, zero;
    wire [1:0] alu_op;
    wire [3:0] alu_ctrl;

    imem IMEM(.addr(pc), .instr(instr));

    control CTRL(.opcode(instr[6:0]), .reg_write(reg_write), .alu_src(alu_src),
        .mem_write(mem_write), .mem_read(mem_read), .mem_to_reg(mem_to_reg),
        .branch(branch), .alu_op(alu_op));

    regfile RF(.clk(clk), .rs1(instr[19:15]), .rs2(instr[24:20]), .rd(instr[11:7]),
        .wd(wb_data), .we(reg_write), .rd1(rd1), .rd2(rd2));

    assign imm = {{20{instr[31]}}, instr[31:20]};      // sign-extend I-type
    assign alu_b = alu_src ? imm : rd2;

    // ALU control decode: combine alu_op with funct3/funct7 for R-type
    assign alu_ctrl = (alu_op == 2'b10) ?
        (instr[30] ? 4'b0001 : (instr[14:12]==3'b111 ? 4'b0010 :
         instr[14:12]==3'b110 ? 4'b0011 : 4'b0000)) :
        (alu_op == 2'b01) ? 4'b0001 : 4'b0000;          // BEQ subtracts

    alu ALU(.a(rd1), .b(alu_b), .alu_ctrl(alu_ctrl), .result(alu_result), .zero(zero));

    dmem DMEM(.clk(clk), .mem_write(mem_write), .mem_read(mem_read),
        .addr(alu_result), .wd(rd2), .rd(mem_rd));

    assign wb_data = mem_to_reg ? mem_rd : alu_result;

    always @(posedge clk or posedge reset) begin
        if (reset) pc <= 0;
        else if (branch && zero) pc <= pc + imm;
        else pc <= pc + 4;
    end
endmodule

tb/cpu_tb.v
module cpu_tb;
    reg clk = 0, reset = 1;
    cpu DUT(.clk(clk), .reset(reset));

    always #5 clk = ~clk;

    initial begin
        $dumpfile("wave.vcd");
        $dumpvars(0, cpu_tb);

        #2 reset = 0;
        #200; // let the program run

        if (DUT.RF.regs[3] == 8)
            $display("PASS: x3 == 8");
        else
            $display("FAIL: x3 = %0d, expected 8", DUT.RF.regs[3]);

        if (DUT.DMEM.mem[0] == 8)
            $display("PASS: mem[0] == 8");
        else
            $display("FAIL: mem[0] = %0d, expected 8", DUT.DMEM.mem[0]);

        $finish;
    end
endmodule

wave.vcd
$date
	Thu Aug 13 00:18:48 2026
$end
$version
	Icarus Verilog
$end
$timescale
	1s
$end
$scope module cpu_tb $end
$var reg 1 ! clk $end
$var reg 1 " reset $end
$scope module DUT $end
$var wire 1 ! clk $end
$var wire 1 " reset $end
$var wire 1 # zero $end
$var wire 32 $ wb_data [31:0] $end
$var wire 1 % reg_write $end
$var wire 32 & rd2 [31:0] $end
$var wire 32 ' rd1 [31:0] $end
$var wire 1 ( mem_write $end
$var wire 1 ) mem_to_reg $end
$var wire 1 * mem_read $end
$var wire 32 + mem_rd [31:0] $end
$var wire 32 , instr [31:0] $end
$var wire 32 - imm [31:0] $end
$var wire 1 . branch $end
$var wire 1 / alu_src $end
$var wire 32 0 alu_result [31:0] $end
$var wire 2 1 alu_op [1:0] $end
$var wire 4 2 alu_ctrl [3:0] $end
$var wire 32 3 alu_b [31:0] $end
$var reg 32 4 pc [31:0] $end
$scope module ALU $end
$var wire 4 5 alu_ctrl [3:0] $end
$var wire 32 6 b [31:0] $end
$var wire 1 # zero $end
$var wire 32 7 a [31:0] $end
$var reg 32 8 result [31:0] $end
$upscope $end
$scope module CTRL $end
$var wire 7 9 opcode [6:0] $end
$var reg 2 : alu_op [1:0] $end
$var reg 1 / alu_src $end
$var reg 1 . branch $end
$var reg 1 * mem_read $end
$var reg 1 ) mem_to_reg $end
$var reg 1 ( mem_write $end
$var reg 1 % reg_write $end
$upscope $end
$scope module DMEM $end
$var wire 32 ; addr [31:0] $end
$var wire 1 ! clk $end
$var wire 1 * mem_read $end
$var wire 1 ( mem_write $end
$var wire 32 < rd [31:0] $end
$var wire 32 = wd [31:0] $end
$upscope $end
$scope module IMEM $end
$var wire 32 > addr [31:0] $end
$var wire 32 ? instr [31:0] $end
$upscope $end
$scope module RF $end
$var wire 1 ! clk $end
$var wire 5 @ rd [4:0] $end
$var wire 5 A rs1 [4:0] $end
$var wire 5 B rs2 [4:0] $end
$var wire 32 C wd [31:0] $end
$var wire 1 % we $end
$var wire 32 D rd2 [31:0] $end
$var wire 32 E rd1 [31:0] $end
$upscope $end
$upscope $end
$upscope $end
$enddefinitions $end
$comment Show the parameter values. $end
$dumpall
$end
#0
$dumpvars
b0 E
bx D
b101 C
b101 B
b0 A
b1 @
b10100000000000010010011 ?
b0 >
bx =
bx <
b101 ;
b0 :
b10011 9
b101 8
b0 7
b101 6
b0 5
b0 4
b101 3
b0 2
b0 1
b101 0
1/
0.
b101 -
b10100000000000010010011 ,
bx +
0*
0)
0(
b0 '
bx &
1%
b101 $
0#
1"
0!
$end
#2
0"
#5
b11 $
b11 C
b11 0
b11 8
b11 ;
b11 3
b11 6
b11 -
b10 @
b11 B
b1100000000000100010011 ,
b1100000000000100010011 ?
b100 4
b100 >
1!
#10
0!
#15
b1000 $
b1000 C
0#
b1000 0
b1000 8
b1000 ;
b11 &
b11 =
b11 D
b101 '
b101 7
b101 E
b11 3
b11 6
b10 -
b10 1
b10 :
1%
0/
b11 @
b10 B
b1 A
b110011 9
b1000001000000110110011 ,
b1000001000000110110011 ?
b1000 4
b1000 >
1!
#20
0!
#25
b101 $
b101 C
b101 0
b101 8
b101 ;
b1 2
b1 5
b1000 '
b1000 7
b1000 E
b10000000010 -
b100 @
b11 A
b1000000001000011000001000110011 ,
b1000000001000011000001000110011 ?
b1100 4
b1100 >
1!
#30
0!
#35
b11 $
b11 C
b11 0
b11 8
b11 ;
b1000 &
b1000 =
b1000 D
b0 '
b0 7
b0 E
b0 2
b0 5
b11 -
1(
1/
0%
b0 1
b0 :
b0 @
b11 B
b0 A
b100011 9
b1100000010000000100011 ,
b1100000010000000100011 ?
b10000 4
b10000 >
1!
#40
0!
#45
1#
b0 0
b0 8
b0 ;
b0 &
b0 =
b0 D
b1000 $
b1000 C
b0 3
b0 6
b0 -
1)
1*
1%
1/
0(
b101 @
b0 B
b11 9
b10001010000011 ,
b10001010000011 ?
b1000 +
b1000 <
b10100 4
b10100 >
1!
#50
0!
#55
b1000 +
b1000 <
b1000 3
b1000 6
1#
b0 0
b0 8
b0 ;
b1 2
b1 5
b1000 &
b1000 =
b1000 D
b1000 '
b1000 7
b1000 E
b0 $
b0 C
b101 -
b1 1
b1 :
1.
0%
0/
0*
0)
b100 @
b101 B
b11 A
b1100011 9
b10100011000001001100011 ,
b10100011000001001100011 ?
b11000 4
b11000 >
1!
#60
0!
#65
bx +
bx <
b1100011 $
b1100011 C
0#
b1100011 0
b1100011 8
b1100011 ;
b0 2
b0 5
b0 '
b0 7
b0 E
b1100011 3
b1100011 6
b1100011 -
1/
1%
0.
b0 1
b0 :
b110 @
b11 B
b0 A
b10011 9
b110001100000000001100010011 ,
b110001100000000001100010011 ?
b11101 4
b11101 >
1!
#70
0!
#75
b1000 +
b1000 <
1#
b0 $
b0 C
b1 2
b1 5
b0 0
b0 8
b0 ;
b1000 '
b1000 7
b1000 E
b1000 3
b1000 6
b11111111111111111111111111100101 -
b1 1
b1 :
1.
0%
0/
b1101 @
b101 B
b11 A
b1100011 9
b11111110010100011000011011100011 ,
b11111110010100011000011011100011 ?
b100001 4
b100001 >
1!
#80
0!
#85
b11 $
b11 C
0#
b11 0
b11 8
b11 ;
b0 2
b0 5
b0 '
b0 7
b0 E
b11 3
b11 6
b11 -
1/
1%
0.
b0 1
b0 :
b10 @
b11 B
b0 A
b10011 9
b1100000000000100010011 ,
b1100000000000100010011 ?
b110 4
b110 >
1!
#90
0!
#95
bx +
bx <
b1000 $
b1000 C
b1000 0
b1000 8
b1000 ;
b11 &
b11 =
b11 D
b101 '
b101 7
b101 E
b11 3
b11 6
b10 -
b10 1
b10 :
1%
0/
b11 @
b10 B
b1 A
b110011 9
b1000001000000110110011 ,
b1000001000000110110011 ?
b1010 4
b1010 >
1!
#100
0!
#105
b101 $
b101 C
b101 0
b101 8
b101 ;
b1 2
b1 5
b1000 '
b1000 7
b1000 E
b10000000010 -
b100 @
b11 A
b1000000001000011000001000110011 ,
b1000000001000011000001000110011 ?
b1110 4
b1110 >
1!
#110
0!
#115
b1000 +
b1000 <
b11 $
b11 C
b11 0
b11 8
b11 ;
b1000 &
b1000 =
b1000 D
b0 '
b0 7
b0 E
b0 2
b0 5
b11 -
1(
1/
0%
b0 1
b0 :
b0 @
b11 B
b0 A
b100011 9
b1100000010000000100011 ,
b1100000010000000100011 ?
b10010 4
b10010 >
1!
#120
0!
#125
1#
b0 0
b0 8
b0 ;
b0 &
b0 =
b0 D
b1000 $
b1000 C
b0 3
b0 6
b0 -
1)
1*
1%
1/
0(
b101 @
b0 B
b11 9
b10001010000011 ,
b10001010000011 ?
b10110 4
b10110 >
1!
#130
0!
#135
b1000 +
b1000 <
b1000 3
b1000 6
1#
b0 0
b0 8
b0 ;
b1 2
b1 5
b1000 &
b1000 =
b1000 D
b1000 '
b1000 7
b1000 E
b0 $
b0 C
b101 -
b1 1
b1 :
1.
0%
0/
0*
0)
b100 @
b101 B
b11 A
b1100011 9
b10100011000001001100011 ,
b10100011000001001100011 ?
b11010 4
b11010 >
1!
#140
0!
#145
bx +
bx <
b1100011 $
b1100011 C
0#
b1100011 0
b1100011 8
b1100011 ;
b0 2
b0 5
b0 '
b0 7
b0 E
b1100011 3
b1100011 6
b1100011 -
1/
1%
0.
b0 1
b0 :
b110 @
b11 B
b0 A
b10011 9
b110001100000000001100010011 ,
b110001100000000001100010011 ?
b11111 4
b11111 >
1!
#150
0!
#155
b1000 +
b1000 <
1#
b0 $
b0 C
b1 2
b1 5
b0 0
b0 8
b0 ;
b1000 '
b1000 7
b1000 E
b1000 3
b1000 6
b11111111111111111111111111100101 -
b1 1
b1 :
1.
0%
0/
b1101 @
b101 B
b11 A
b1100011 9
b11111110010100011000011011100011 ,
b11111110010100011000011011100011 ?
b100011 4
b100011 >
1!
#160
0!
#165
bx +
bx <
b1000 $
b1000 C
b11 3
b11 6
0#
b1000 0
b1000 8
b1000 ;
b11 &
b11 =
b11 D
b101 '
b101 7
b101 E
b0 2
b0 5
b10 -
1%
0.
b10 1
b10 :
b11 @
b10 B
b1 A
b110011 9
b1000001000000110110011 ,
b1000001000000110110011 ?
b1000 4
b1000 >
1!
#170
0!
#175
b101 $
b101 C
b101 0
b101 8
b101 ;
b1 2
b1 5
b1000 '
b1000 7
b1000 E
b10000000010 -
b100 @
b11 A
b1000000001000011000001000110011 ,
b1000000001000011000001000110011 ?
b1100 4
b1100 >
1!
#180
0!
#185
b1000 +
b1000 <
b11 $
b11 C
b11 0
b11 8
b11 ;
b1000 &
b1000 =
b1000 D
b0 '
b0 7
b0 E
b0 2
b0 5
b11 -
1(
1/
0%
b0 1
b0 :
b0 @
b11 B
b0 A
b100011 9
b1100000010000000100011 ,
b1100000010000000100011 ?
b10000 4
b10000 >
1!
#190
0!
#195
1#
b0 0
b0 8
b0 ;
b0 &
b0 =
b0 D
b1000 $
b1000 C
b0 3
b0 6
b0 -
1)
1*
1%
1/
0(
b101 @
b0 B
b11 9
b10001010000011 ,
b10001010000011 ?
b10100 4
b10100 >
1!
